{
  "uid" : "57517ab78d97d6f0",
  "name" : "Should verify created user in User List",
  "title" : "Should verify created user in User List",
  "time" : {
    "start" : 1461766571085,
    "stop" : 1461766575168,
    "duration" : 4083
  },
  "summary" : {
    "attachments" : 0,
    "steps" : 0
  },
  "failure" : null,
  "description" : {
    "value" : "",
    "type" : "TEXT"
  },
  "severity" : "NORMAL",
  "status" : "PASSED",
  "testId" : null,
  "suite" : {
    "uid" : "5b3726596a74b96",
    "name" : "Car2goweb application:",
    "title" : "Car2goweb application:"
  },
  "steps" : [ ],
  "attachments" : [ ],
  "issues" : [ ],
  "labels" : [ {
    "name" : "suite-name",
    "value" : "Car2goweb application:"
  }, {
    "name" : "suite-title",
    "value" : "Car2goweb application:"
  } ],
  "parameters" : [ ]
}